rsbackup/__init__.py
rsbackup/__main__.py
rsbackup/main_test.py
rsbackup/rsbackup_test.py
rsbackup-0.4.0.dist-info/LICENSE
rsbackup-0.4.0.dist-info/METADATA
rsbackup-0.4.0.dist-info/WHEEL
rsbackup-0.4.0.dist-info/entry_points.txt
rsbackup-0.4.0.dist-info/top_level.txt
rsbackup-0.4.0.dist-info/zip-safe
rsbackup-0.4.0.dist-info/RECORD
