Metadata-Version: 2.1
Name: rsbackup
Version: 0.4.0
Summary: Backup for unix-like systems using rsync.
Home-page: https://github.com/halimath/rsbackup
Author: Alexander Metzner
Author-email: alexander.metzner@gmail.com
License: Apache
Classifier: Development Status :: 4 - Beta
Classifier: Environment :: Console
Classifier: Intended Audience :: System Administrators
Classifier: License :: OSI Approved :: Apache Software License
Classifier: Natural Language :: English
Classifier: Operating System :: POSIX
Classifier: Programming Language :: Python :: 3.10
Classifier: Programming Language :: Python :: 3.11
Classifier: Topic :: System :: Archiving :: Backup
Classifier: Topic :: Utilities
Requires-Python: >=3.10
License-File: LICENSE
Requires-Dist: tomli
Requires-Dist: termapp (>=0.1.2)
Requires-Dist: aiofiles
